msvproperties/__init__.py
msvproperties/api.py
msvproperties/auth.py
msvproperties/config.py
msvproperties/core.py
msvproperties/data_handling.py
msvproperties/data_models.py
msvproperties/data_types.py
msvproperties/logger.py
msvproperties/process.py
msvproperties/utils.py
tests/__init__.py
tests/test.py
msvproperties-1.3.4.dist-info/LICENSE
msvproperties-1.3.4.dist-info/METADATA
msvproperties-1.3.4.dist-info/WHEEL
msvproperties-1.3.4.dist-info/top_level.txt
msvproperties-1.3.4.dist-info/RECORD
