Metadata-Version: 2.2
Name: msvproperties
Version: 1.3.4
Summary: A Library for using in our CRM
Home-page: https://github.com/alireza-msvproperties/msvproperties/
Author: Alireza
Author-email: alireza@msvproperties.net
License: MIT
Classifier: Programming Language :: Python :: 3
Classifier: Programming Language :: Python :: 3.13
Classifier: License :: OSI Approved :: MIT License
Requires-Python: <4
License-File: LICENSE
Dynamic: author
Dynamic: author-email
Dynamic: classifier
Dynamic: home-page
Dynamic: license
Dynamic: requires-python
Dynamic: summary
